slrquerytester/__init__.py
slrquerytester/__main__.py
slrquerytester/connectors/__init__.py
slrquerytester/connectors/base_connector.py
slrquerytester/connectors/connector_exceptions.py
slrquerytester/connectors/core_connector.py
slrquerytester/connectors/dimensions_connector.py
slrquerytester/connectors/ieee_connector.py
slrquerytester/connectors/lens_connector.py
slrquerytester/connectors/openalex_connector.py
slrquerytester/connectors/scopus_connector.py
slrquerytester/connectors/springer_connector.py
slrquerytester/connectors/wos_connector.py
slrquerytester/connectors/sdks/__init__.py
slrquerytester/connectors/sdks/xploreapi.py
slrquerytester/translators/__init__.py
slrquerytester/translators/base_transformer.py
slrquerytester/translators/core_transformer.py
slrquerytester/translators/dimensions_transformer.py
slrquerytester/translators/ieee_transformer.py
slrquerytester/translators/lens_transformer.py
slrquerytester/translators/openalex_transformer.py
slrquerytester/translators/query_translator.py
slrquerytester/translators/scopus_transformer.py
slrquerytester/translators/springer_transformer.py
slrquerytester/translators/wos_transformer.py
slrquerytester/utils/__init__.py
slrquerytester/utils/cache_manager.py
slrquerytester/utils/connector_manager.py
slrquerytester/utils/document_generator.py
slrquerytester/utils/file_manager.py
slrquerytester/utils/query_parser.py
slrquerytester/utils/query_processor.py
slrquerytester/utils/report_generator.py
slrquerytester-0.2.1.dist-info/licenses/LICENSE
slrquerytester-0.2.1.dist-info/METADATA
slrquerytester-0.2.1.dist-info/WHEEL
slrquerytester-0.2.1.dist-info/entry_points.txt
slrquerytester-0.2.1.dist-info/top_level.txt
slrquerytester-0.2.1.dist-info/RECORD
