Metadata-Version: 2.4
Name: slrquerytester
Version: 0.2.1
Summary: A Python toolkit to test queries across multiple bibliographic databases for Systematic Literature Reviews
Author-email: Rakshit Mittal <pypi@rakshitmittal.net>
License-Expression: MIT
Project-URL: Homepage, https://gitlab.rakshitmittal.net/rmittal/slrquerytester
Requires-Python: >=3.11
License-File: LICENSE
Requires-Dist: pdoc~=15.0.1
Requires-Dist: lark~=1.2.2
Requires-Dist: langcodes~=3.5.0
Requires-Dist: bibtexparser~=2.0.0b8
Requires-Dist: requests~=2.32.3
Requires-Dist: fuzzywuzzy~=0.18.0
Requires-Dist: backoff~=2.2.1
Requires-Dist: pdoc~=15.0.1
Requires-Dist: pycurl~=7.45.4
Requires-Dist: certifi~=2025.1.31
Requires-Dist: dimcli~=1.4
Dynamic: license-file
